utts/__init__.py
utts/base.py
utts/cartesia.py
utts/client.py
utts/elevenlabs.py
utts/hume.py
utts/kokoro.py
utts/openai.py
utts/orpheus.py
utts/py.typed
utts/replicate.py
utts/utils.py
utts/zyphra.py
utts-0.1.3.dist-info/METADATA
utts-0.1.3.dist-info/WHEEL
utts-0.1.3.dist-info/licenses/LICENSE
utts-0.1.3.dist-info/RECORD
