Metadata-Version: 2.4
Name: utts
Version: 0.1.3
Summary: Universal interface to test and compare text-to-speech providers
Author-email: Dave Savostyanov <ds@artifactory.ai>
License: MIT
License-File: LICENSE
Classifier: Programming Language :: Python :: 3
Requires-Python: >=3.11.12
Requires-Dist: cartesia>=2.0.2
Requires-Dist: elevenlabs>=1.57.0
Requires-Dist: hume>=0.8.3
Requires-Dist: nest-asyncio>=1.6.0
Requires-Dist: openai>=1.76.2
Requires-Dist: pandas>=2.2.2
Requires-Dist: replicate>=1.0.6
Requires-Dist: timeout-function-decorator>=2.0.0
Requires-Dist: zyphra>=0.1.6
